set_up.py
setup.py
huoyanlib/__init__.py
huoyanlib/c.py
huoyanlib/help.py
huoyanlib/log_in.py
huoyanlib/print.py
huoyanlib/print_logo.py
huoyanlib/python_plot.py
huoyanlib/spark_word.py
huoyanlib-games/__init__.py
huoyanlib-games/ballballball.py
huoyanlib-games/hit_the_block.py
huoyanlib-games/practise_typing.py
huoyanlib-games/snake.py
huoyanlib/numpy/__init__.py
huoyanlib/numpy/f.py
huoyanlib/request/__init__.py
huoyanlib/request/get_news.py
huoyanlib/request/internal_module.py
huoyanlib/request/xes.py
huoyanlib_games.egg-info/PKG-INFO
huoyanlib_games.egg-info/SOURCES.txt
huoyanlib_games.egg-info/dependency_links.txt
huoyanlib_games.egg-info/top_level.txt