Metadata-Version: 2.1
Name: huoyanlib-games
Version: 0.0.1
Summary: 学而思火焰工作室专属游戏库（如果常规线路无法下载，请尝试其他线路）
Home-page: https://github.com/
Author: Ruiqin-Li
Author-email: 2647154420@qq.com
License: UNKNOWN
Platform: UNKNOWN
Classifier: Programming Language :: Python :: 3
Classifier: License :: OSI Approved :: MIT License
Classifier: Operating System :: OS Independent
